clem2itunes/__init__.py
clem2itunes/__main__.py
clem2itunes/main.py
clem2itunes/py.typed
clem2itunes/utils.py
clem2itunes-0.1.2.dist-info/LICENSE.txt
clem2itunes-0.1.2.dist-info/METADATA
clem2itunes-0.1.2.dist-info/WHEEL
clem2itunes-0.1.2.dist-info/entry_points.txt
clem2itunes-0.1.2.dist-info/RECORD
