Metadata-Version: 2.3
Name: clem2itunes
Version: 0.1.2
Summary: Crazy way to synchronise a remote Strawberry rated library to Music.app using Python, JXA and SSH.
License: MIT
Keywords: command line,file management,multimedia,macos,ssh,strawberry
Author: Andrew Udvare
Author-email: audvare@gmail.com
Requires-Python: >=3.10,<3.14
Classifier: Development Status :: 2 - Pre-Alpha
Classifier: Intended Audience :: Developers
Classifier: License :: OSI Approved :: MIT License
Classifier: Programming Language :: Python
Classifier: Programming Language :: Python :: 3.10
Classifier: Programming Language :: Python :: 3.11
Classifier: Programming Language :: Python :: 3.12
Classifier: Programming Language :: Python :: 3.13
Classifier: Typing :: Typed
Requires-Dist: aiosqlite (>=0.21.0,<0.22.0)
Requires-Dist: anyio (>=4.9.0,<5.0.0)
Requires-Dist: click (>=8.2.0,<9.0.0)
Requires-Dist: click-aliases (>=1.0.5,<2.0.0)
Requires-Dist: colorlog (>=6.9.0,<7.0.0)
Requires-Dist: platformdirs (>=4.3.6,<5.0.0)
Requires-Dist: typing-extensions (>=4.13.1,<5.0.0)
Project-URL: Documentation, https://clem2itunes.readthedocs.org
Project-URL: Homepage, https://tatsh.github.io/clem2itunes/
Project-URL: Issues, https://github.com/Tatsh/clem2itunes/issues
Project-URL: Repository, https://github.com/Tatsh/clem2itunes
